CHANGES.txt
COPYING.txt
MANIFEST.in
README.txt
ez_setup.py
setup.cfg
setup.py
edbob/__init__.py
edbob/_version.py
edbob/commands.py
edbob/configuration.py
edbob/console.py
edbob/core.py
edbob/csv.py
edbob/daemon.py
edbob/enum.py
edbob/errors.py
edbob/exceptions.py
edbob/files.py
edbob/initialization.py
edbob/mail.py
edbob/modules.py
edbob/sqlalchemy.py
edbob/time.py
edbob/util.py
edbob/win32.py
edbob.egg-info/PKG-INFO
edbob.egg-info/SOURCES.txt
edbob.egg-info/dependency_links.txt
edbob.egg-info/entry_points.txt
edbob.egg-info/not-zip-safe
edbob.egg-info/requires.txt
edbob.egg-info/top_level.txt
edbob/db/__init__.py
edbob/db/auth.py
edbob/db/classes.py
edbob/db/enum.py
edbob/db/exceptions.py
edbob/db/mappers.py
edbob/db/model.py
edbob/db/util.py
edbob/db/extensions/__init__.py
edbob/db/extensions/auth/__init__.py
edbob/db/extensions/auth/model.py
edbob/db/extensions/contact/__init__.py
edbob/db/extensions/contact/model.py
edbob/filemon/__init__.py
edbob/filemon/linux.py
edbob/filemon/win32.py
edbob/lib/__init__.py
edbob/lib/pretty.py
edbob/pyramid/__init__.py
edbob/pyramid/auth.py
edbob/pyramid/filters.py
edbob/pyramid/helpers.py
edbob/pyramid/progress.py
edbob/pyramid/subscribers.py
edbob/pyramid/tweens.py
edbob/pyramid/forms/__init__.py
edbob/pyramid/forms/core.py
edbob/pyramid/forms/simpleform.py
edbob/pyramid/forms/formalchemy/__init__.py
edbob/pyramid/forms/formalchemy/fields.py
edbob/pyramid/forms/formalchemy/fieldset.py
edbob/pyramid/forms/formalchemy/renderers.py
edbob/pyramid/grids/__init__.py
edbob/pyramid/grids/alchemy.py
edbob/pyramid/grids/core.py
edbob/pyramid/grids/search.py
edbob/pyramid/grids/util.py
edbob/pyramid/static/__init__.py
edbob/pyramid/static/favicon.ico
edbob/pyramid/static/robots.txt
edbob/pyramid/static/css/autocomplete.css
edbob/pyramid/static/css/base.css
edbob/pyramid/static/css/filters.css
edbob/pyramid/static/css/forms.css
edbob/pyramid/static/css/grids.css
edbob/pyramid/static/css/layout.css
edbob/pyramid/static/css/login.css
edbob/pyramid/static/css/perms.css
edbob/pyramid/static/css/smoothness/jquery-ui-1.8.2.custom.css
edbob/pyramid/static/css/smoothness/images/ui-anim_basic_16x16.gif
